edapro/__init__.py
edapro/edapro.py
edapro/iris.py
edapro-0.0.2.dist-info/METADATA
edapro-0.0.2.dist-info/WHEEL
edapro-0.0.2.dist-info/top_level.txt
edapro-0.0.2.dist-info/RECORD
