Metadata-Version: 2.1
Name: edapro
Version: 0.0.2
Summary: EDA
Home-page: https://github.com/...
Author: Dheiver Santos
Author-email: dheiver.santos@gmail.com
License: UNKNOWN
Download-URL: https://github.com/...
Platform: UNKNOWN
Classifier: Programming Language :: Python :: 3
Classifier: License :: OSI Approved :: MIT License
Classifier: Operating System :: OS Independent
Requires-Python: >=3.6
